cloudcheckr_cmx/__init__.py
cloudcheckr_cmx/api_client.py
cloudcheckr_cmx/configuration.py
cloudcheckr_cmx/rest.py
cloudcheckr_cmx/api/__init__.py
cloudcheckr_cmx/api/account_attributes_api.py
cloudcheckr_cmx/api/account_management_api.py
cloudcheckr_cmx/api/accounts_api.py
cloudcheckr_cmx/api/client_access_keys_api.py
cloudcheckr_cmx/api/clients_api.py
cloudcheckr_cmx/api/custom_theme_settings_api.py
cloudcheckr_cmx/api/customers_api.py
cloudcheckr_cmx/api/permission_sets_api.py
cloudcheckr_cmx/api/permissions_api.py
cloudcheckr_cmx/api/roles_api.py
cloudcheckr_cmx/api/saml_provider_rules_api.py
cloudcheckr_cmx/api/saml_providers_api.py
cloudcheckr_cmx/api/token_management_api.py
cloudcheckr_cmx/api/users_api.py
cloudcheckr_cmx/models/__init__.py
cloudcheckr_cmx/models/account_assignment_response_model.py
cloudcheckr_cmx/models/account_attribute_assignment_response_model.py
cloudcheckr_cmx/models/account_attribute_basic_info.py
cloudcheckr_cmx/models/account_attribute_modification.py
cloudcheckr_cmx/models/account_attribute_request_model.py
cloudcheckr_cmx/models/account_attribute_response_model.py
cloudcheckr_cmx/models/account_cost.py
cloudcheckr_cmx/models/account_group_hierarchy_response_model.py
cloudcheckr_cmx/models/account_group_request_model.py
cloudcheckr_cmx/models/account_group_response_model.py
cloudcheckr_cmx/models/account_group_search_response_model.py
cloudcheckr_cmx/models/ancestor_model.py
cloudcheckr_cmx/models/ancestors_response_model.py
cloudcheckr_cmx/models/base_account_info.py
cloudcheckr_cmx/models/basic_request_list_modification.py
cloudcheckr_cmx/models/bulk_account_assignment_request_model.py
cloudcheckr_cmx/models/bulk_account_assignment_response_model_account_assignment_response_model.py
cloudcheckr_cmx/models/bulk_account_assignment_response_model_account_attribute_assignment_response_model.py
cloudcheckr_cmx/models/bulk_account_attribute_assignment_request_model.py
cloudcheckr_cmx/models/client_access_key_request_model.py
cloudcheckr_cmx-0.2.0.dist-info/METADATA
cloudcheckr_cmx-0.2.0.dist-info/WHEEL
cloudcheckr_cmx-0.2.0.dist-info/top_level.txt
cloudcheckr_cmx-0.2.0.dist-info/RECORD
